dostoevsky/__init__.py
dostoevsky/__main__.py
dostoevsky/corpora.py
dostoevsky/models.py
dostoevsky/tokenization.py
dostoevsky/data/__init__.py
dostoevsky/data/corpora/__init__.py
dostoevsky/data/models/__init__.py
dostoevsky/tests/__init__.py
dostoevsky/tests/conftest.py
dostoevsky/tests/test_corpora.py
dostoevsky/tests/test_tokenization.py
dostoevsky-0.5.0.data/scripts/dostoevsky
dostoevsky-0.5.0.dist-info/LICENSE
dostoevsky-0.5.0.dist-info/METADATA
dostoevsky-0.5.0.dist-info/WHEEL
dostoevsky-0.5.0.dist-info/top_level.txt
dostoevsky-0.5.0.dist-info/RECORD
