Metadata-Version: 2.1
Name: dostoevsky
Version: 0.5.0
Summary: Sentiment analysis library for russian language
Home-page: https://github.com/bureaucratic-labs/dostoevsky
Author: Bureaucratic Labs
Author-email: hello@b-labs.pro
License: MIT
Keywords: natural language processing,sentiment analysis
Platform: UNKNOWN
Classifier: Development Status :: 3 - Alpha
Classifier: Intended Audience :: Developers
Classifier: Intended Audience :: Science/Research
Classifier: License :: OSI Approved :: MIT License
Classifier: Programming Language :: Python
Classifier: Programming Language :: Python :: 3.6
Classifier: Programming Language :: Python :: 3.7
Classifier: Programming Language :: Python :: Implementation :: CPython
Classifier: Topic :: Software Development :: Libraries :: Python Modules
Classifier: Topic :: Scientific/Engineering :: Information Analysis
Classifier: Topic :: Text Processing :: Linguistic
